papervibe/__init__.py
papervibe/arxiv.py
papervibe/cli.py
papervibe/compile.py
papervibe/highlight.py
papervibe/latex.py
papervibe/llm.py
papervibe/logging.py
papervibe/process.py
papervibe/prompts.py
papervibe/prompts/highlight_system.j2
papervibe/prompts/highlight_user.j2
papervibe/prompts/rewrite_abstract_system.j2
papervibe/prompts/rewrite_abstract_user.j2
papervibe-0.1.0a1.dist-info/METADATA
papervibe-0.1.0a1.dist-info/WHEEL
papervibe-0.1.0a1.dist-info/entry_points.txt
papervibe-0.1.0a1.dist-info/licenses/LICENSE
papervibe-0.1.0a1.dist-info/RECORD
