Metadata-Version: 2.4
Name: papervibe
Version: 0.1.0a1
Summary: Tool to download arXiv papers, rewrite abstracts, and highlight important content
Project-URL: Homepage, https://github.com/deltazefiro/papervibe
Project-URL: Repository, https://github.com/deltazefiro/papervibe
Project-URL: Issues, https://github.com/deltazefiro/papervibe/issues
Author-email: deltazefiro <deltazefiro@gmail.com>
License: GPL-3.0-or-later
License-File: LICENSE
Keywords: ai,arxiv,latex,llm,openai,pdf,research
Classifier: Development Status :: 3 - Alpha
Classifier: Environment :: Console
Classifier: Intended Audience :: Science/Research
Classifier: License :: OSI Approved :: GNU General Public License v3 or later (GPLv3+)
Classifier: Operating System :: OS Independent
Classifier: Programming Language :: Python :: 3
Classifier: Programming Language :: Python :: 3.11
Classifier: Programming Language :: Python :: 3.12
Classifier: Programming Language :: Python :: 3.13
Classifier: Topic :: Scientific/Engineering
Classifier: Topic :: Text Processing :: Markup :: LaTeX
Classifier: Typing :: Typed
Requires-Python: >=3.11
Requires-Dist: httpx>=0.27.0
Requires-Dist: jinja2>=3.1.0
Requires-Dist: openai>=1.0.0
Requires-Dist: pydantic-settings>=2.0.0
Requires-Dist: pydantic>=2.0.0
Requires-Dist: pylatexenc>=2.10
Requires-Dist: python-dotenv>=1.0.0
Requires-Dist: rich>=13.0.0
Requires-Dist: tenacity>=8.2.3
Requires-Dist: typer>=0.12.0
